<mujoco model="uav_env">
  <compiler angle="degree" coordinate="local" inertiafromgeom="true"/>
  <option integrator="RK4" timestep="0.01"/>
  <asset>
    <texture type="skybox" builtin="gradient" rgb1="0.3 0.5 0.7" rgb2="0 0 0" width="512" height="3072"/>
    <texture name="grid" type="2d" builtin="checker" rgb1="0.1 0.2 0.3" rgb2="0.2 0.3 0.4" width="512" height="512"/>
    <material name="grid" texture="grid" texrepeat="1 1" reflectance="0.2"/>
  </asset>
  <worldbody>
    <geom name="ground" type="plane" size="4.0 4.0 0.1" material="grid"/>
    <light name="light1" pos="0 0 4" dir="0 0 -1" diffuse="1 1 1"/>
    <body name="chassis" pos="3.0 -3.0 1.0">
      <joint type="free" name="root"/>
      <geom type="box" size="0.12 0.12 0.02" rgba="1.0 0.0 0.0 1.0" mass="0.8"/>
      <site name="motor1" pos="0.08 0.08 0" size="0.01"/>
      <site name="motor2" pos="-0.08 0.08 0" size="0.01"/>
      <site name="motor3" pos="0.08 -0.08 0" size="0.01"/>
      <site name="motor4" pos="-0.08 -0.08 0" size="0.01"/>
    </body>
    <geom name="static_obs_0" type="cylinder" size="0.10092913924341781 1.0" pos="-0.7813374625085951 2.8491962375984623 1.0" rgba="0.10203641905421845 0.6012007776645893 0.7317804646063121 1.0"/>
    <geom name="static_obs_1" type="box" size="0.1183827340263497 0.06912241720569949 1.0" pos="2.647396651699262 3.090033919042813 1.0" rgba="0.3089782109030228 0.3295778282062869 0.17557523323087923 1.0"/>
    <geom name="static_obs_2" type="box" size="0.10904316417160956 0.06297825531087504 1.0" pos="3.07407484083648 1.2055799800299791 1.0" rgba="0.7949579504332133 0.3981327426282195 0.212110861850618 1.0"/>
    <geom name="static_obs_3" type="cylinder" size="0.05383496818657604 1.0" pos="-3.0596457970876973 1.4817416473877243 1.0" rgba="0.24546486099066123 0.7497383338130686 0.8932893286040515 1.0"/>
    <geom name="static_obs_4" type="cylinder" size="0.07809799498269228 1.0" pos="3.319202736578621 -1.3088975178225475 1.0" rgba="0.8421287056007838 0.24507339821193047 0.8367657107206091 1.0"/>
    <geom name="static_obs_5" type="box" size="0.09713256293289756 0.07051950757195913 1.0" pos="-1.2291306261341344 1.46121665370235 1.0" rgba="0.4882312194942665 0.8185698537735983 0.18496817737877685 1.0"/>
    <geom name="static_obs_6" type="box" size="0.114323769614736 0.08539428885558134 1.0" pos="0.5002369383441493 0.911111828003448 1.0" rgba="0.26009039633920916 0.8825227280358074 0.8603417810600202 1.0"/>
    <geom name="static_obs_7" type="cylinder" size="0.0682619501859372 1.0" pos="-1.1625243470902276 -2.9367936995322053 1.0" rgba="0.5704943296000097 0.5279670559347807 0.39963137953540007 1.0"/>
    <geom name="static_obs_8" type="cylinder" size="0.06775799804213559 1.0" pos="0.6532667132865801 -3.1964164131543935 1.0" rgba="0.18725667816784997 0.7992119779279847 0.25862904303664935 1.0"/>
    <geom name="static_obs_9" type="box" size="0.05270343804294532 0.05132622106608654 1.0" pos="0.7653169184478954 3.4088481848169216 1.0" rgba="0.6785548017115157 0.6357598587566287 0.6466604092188094 1.0"/>
  </worldbody>
  <actuator>
    <motor name="m1" gear="0 0 1 0 0 0" site="motor1"/>
    <motor name="m2" gear="0 0 1 0 0 0" site="motor2"/>
    <motor name="m3" gear="0 0 1 0 0 0" site="motor3"/>
    <motor name="m4" gear="0 0 1 0 0 0" site="motor4"/>
  </actuator>
</mujoco>